{
	"format_version": "1.12.0",
	"minecraft:geometry": [
		{
			"description": {
				"identifier": "geometry.unknown",
				"texture_width": 16,
				"texture_height": 16,
				"visible_bounds_width": 10,
				"visible_bounds_height": 7,
				"visible_bounds_offset": [0, 1.5, 0]
			},
			"bones": [
				{
					"name": "main",
					"pivot": [0, 12, 0]
				},
				{
					"name": "handle",
					"parent": "main",
					"pivot": [0, -50, 0],
					"cubes": [
						{
							"origin": [-1, -35, -1],
							"size": [2, 68, 2],
							"uv": {
								"north": {"uv": [15.5, 0], "uv_size": [0.5, 12]},
								"east": {"uv": [15.5, 0], "uv_size": [0.5, 12]},
								"south": {"uv": [15.5, 0], "uv_size": [0.5, 12]},
								"west": {"uv": [15.5, 0], "uv_size": [0.5, 12]},
								"up": {"uv": [16, 0.5], "uv_size": [-0.5, -0.5]},
								"down": {"uv": [16, 0.5], "uv_size": [-0.5, -0.5]}
							}
						}
					]
				},
				{
					"name": "bot_part",
					"parent": "handle",
					"pivot": [0, -40, 0],
					"cubes": [
						{
							"origin": [-1.25, -32, -1.25],
							"size": [2.5, 10, 2.5],
							"uv": {
								"north": {"uv": [15.5, 2.5], "uv_size": [0.5, 5.75]},
								"east": {"uv": [15.5, 2.5], "uv_size": [0.5, 5.75]},
								"south": {"uv": [15.5, 2.5], "uv_size": [0.5, 5.75]},
								"west": {"uv": [15.5, 2.5], "uv_size": [0.5, 5.75]},
								"up": {"uv": [16, 0.5], "uv_size": [-0.5, -0.5]},
								"down": {"uv": [16, 0.5], "uv_size": [-0.5, -0.5]}
							}
						}
					]
				},
				{
					"name": "scythe",
					"parent": "main",
					"pivot": [0, -13, 0]
				},
				{
					"name": "holder",
					"parent": "scythe",
					"pivot": [0, -13, 0],
					"cubes": [
						{
							"origin": [-3, 37, -2],
							"size": [6, 2, 4],
							"uv": {
								"north": {"uv": [0, 0], "uv_size": [1.5, 0.5]},
								"east": {"uv": [0, 0], "uv_size": [0.5, 0.5]},
								"south": {"uv": [0, 0], "uv_size": [1.5, 0.5]},
								"west": {"uv": [0, 0], "uv_size": [0.5, 0.5]},
								"up": {"uv": [1.5, 1], "uv_size": [-1.5, -1]},
								"down": {"uv": [1.5, 1], "uv_size": [-1.5, -1]}
							}
						},
						{
							"origin": [-2, 33, -1],
							"size": [4, 4, 2],
							"uv": {
								"north": {"uv": [0, 0], "uv_size": [1, 1]},
								"east": {"uv": [0, 0], "uv_size": [0.5, 1]},
								"south": {"uv": [0, 0], "uv_size": [1, 1]},
								"west": {"uv": [0, 0], "uv_size": [0.5, 1]},
								"up": {"uv": [1, 0.5], "uv_size": [-1, -0.5]},
								"down": {"uv": [1, 0.5], "uv_size": [-1, -0.5]}
							}
						},
						{
							"origin": [1.41421, 38.82843, -1.999],
							"size": [3, 2, 3.998],
							"pivot": [4.41421, 39.82843, -0.001],
							"rotation": [0, 0, -45],
							"uv": {
								"north": {"uv": [0, 0.5], "uv_size": [0.75, 0.5]},
								"east": {"uv": [0, 0], "uv_size": [0.25, 0.25]},
								"south": {"uv": [0, 0.5], "uv_size": [0.75, 0.5]},
								"west": {"uv": [0, 0], "uv_size": [0.25, 0.25]},
								"up": {"uv": [0.75, 1], "uv_size": [-0.75, -0.5]},
								"down": {"uv": [0.75, 1], "uv_size": [-0.75, -0.5]}
							}
						},
						{
							"origin": [-5.66421, 38.82843, -1.999],
							"size": [4.25, 2, 3.998],
							"pivot": [-4.41421, 39.82843, -0.001],
							"rotation": [0, 0, 45],
							"uv": {
								"north": {"uv": [0, 0.5], "uv_size": [1, 0.5]},
								"east": {"uv": [0, 0], "uv_size": [0.25, 0.25]},
								"south": {"uv": [0, 0.5], "uv_size": [1, 0.5]},
								"west": {"uv": [0, 0], "uv_size": [0.25, 0.25]},
								"up": {"uv": [1, 1], "uv_size": [-1, -0.5]},
								"down": {"uv": [1, 1], "uv_size": [-1, -0.5]}
							}
						}
					]
				},
				{
					"name": "main_scythe",
					"parent": "scythe",
					"pivot": [0, -13, 0]
				},
				{
					"name": "inner",
					"parent": "main_scythe",
					"pivot": [0, -15, 0.75],
					"cubes": [
						{
							"origin": [-6.0433, 39.01759, -0.25],
							"size": [13, 7.25, 0.5],
							"uv": {
								"north": {"uv": [7.75, 8], "uv_size": [3.75, 2]},
								"east": {"uv": [0, 0], "uv_size": [0.25, 0.25]},
								"south": {"uv": [11.5, 8], "uv_size": [-3.75, 2]},
								"west": {"uv": [0, 0], "uv_size": [0.25, 0.25]},
								"up": {"uv": [0.25, 0.25], "uv_size": [-0.25, -0.25]},
								"down": {"uv": [0.25, 0.25], "uv_size": [-0.25, -0.25]}
							}
						},
						{
							"origin": [6.9567, 40.76759, -0.25],
							"size": [7, 2.5, 0.5],
							"uv": {
								"north": {"uv": [6.25, 6], "uv_size": [2.75, 1]},
								"east": {"uv": [0, 0], "uv_size": [0.25, 0.25]},
								"south": {"uv": [10.75, 6], "uv_size": [2.75, 1]},
								"west": {"uv": [0, 0], "uv_size": [0.25, 0.25]},
								"up": {"uv": [0.25, 0.25], "uv_size": [-0.25, -0.25]},
								"down": {"uv": [0.25, 0.25], "uv_size": [-0.25, -0.25]}
							}
						},
						{
							"origin": [6.9567, 52.26759, -0.25],
							"size": [9, 2.75, 0.5],
							"uv": {
								"north": {"uv": [8, 5.5], "uv_size": [2.75, 1]},
								"east": {"uv": [0, 0], "uv_size": [0.25, 0.25]},
								"south": {"uv": [10.75, 5.5], "uv_size": [-2.75, 1]},
								"west": {"uv": [0, 0], "uv_size": [0.25, 0.25]},
								"up": {"uv": [0.25, 0.25], "uv_size": [-0.25, -0.25]},
								"down": {"uv": [0.25, 0.25], "uv_size": [-0.25, -0.25]}
							}
						},
						{
							"origin": [15.9567, 52.26759, -0.25],
							"size": [1.75, 1.5, 0.5],
							"uv": {
								"north": {"uv": [9, 1.75], "uv_size": [0.75, 0.5]},
								"east": {"uv": [0, 0], "uv_size": [0.25, 0.25]},
								"south": {"uv": [9, 1.75], "uv_size": [0.75, 0.5]},
								"west": {"uv": [0, 0], "uv_size": [0.25, 0.25]},
								"up": {"uv": [0.25, 0.25], "uv_size": [-0.25, -0.25]},
								"down": {"uv": [0.25, 0.25], "uv_size": [-0.25, -0.25]}
							}
						},
						{
							"origin": [-19.0433, 46.26759, -0.25],
							"size": [26, 10.25, 0.5],
							"uv": {
								"north": {"uv": [7.5, 5.5], "uv_size": [4.75, 3.25]},
								"east": {"uv": [0, 0], "uv_size": [0.25, 0.25]},
								"south": {"uv": [12.25, 5.5], "uv_size": [-4.75, 3.25]},
								"west": {"uv": [0, 0], "uv_size": [0.25, 0.25]},
								"up": {"uv": [0.25, 0.25], "uv_size": [-0.25, -0.25]},
								"down": {"uv": [0.25, 0.25], "uv_size": [-0.25, -0.25]}
							}
						},
						{
							"origin": [-19.0433, 37.01759, -0.25],
							"size": [13, 3.5, 0.5],
							"uv": {
								"north": {"uv": [6, 10], "uv_size": [3.25, 1]},
								"east": {"uv": [0, 0], "uv_size": [0.25, 0.25]},
								"south": {"uv": [9.25, 10], "uv_size": [-3.25, 1]},
								"west": {"uv": [0, 0], "uv_size": [0.25, 0.25]},
								"up": {"uv": [0.25, 0.25], "uv_size": [-0.25, -0.25]},
								"down": {"uv": [0.25, 0.25], "uv_size": [-0.25, -0.25]}
							}
						},
						{
							"origin": [-11.5433, 31.51759, -0.25],
							"size": [4, 5.5, 0.5],
							"uv": {
								"north": {"uv": [8.75, 9.75], "uv_size": [1, 1.25]},
								"east": {"uv": [0, 0], "uv_size": [0.25, 0.25]},
								"south": {"uv": [9.75, 9.75], "uv_size": [-1, 1.25]},
								"west": {"uv": [0, 0], "uv_size": [0.25, 0.25]},
								"up": {"uv": [0.25, 0.25], "uv_size": [-0.25, -0.25]},
								"down": {"uv": [0.25, 0.25], "uv_size": [-0.25, -0.25]}
							}
						},
						{
							"origin": [-14.0433, 34.26759, -0.25],
							"size": [2.5, 2.75, 0.5],
							"uv": {
								"north": {"uv": [7.75, 9.75], "uv_size": [0.75, 0.75]},
								"east": {"uv": [0, 0], "uv_size": [0.25, 0.25]},
								"south": {"uv": [8.5, 9.75], "uv_size": [-0.75, 0.75]},
								"west": {"uv": [0, 0], "uv_size": [0.25, 0.25]},
								"up": {"uv": [0.25, 0.25], "uv_size": [-0.25, -0.25]},
								"down": {"uv": [0.25, 0.25], "uv_size": [-0.25, -0.25]}
							}
						},
						{
							"origin": [6.9567, 43.26759, -0.25],
							"size": [23, 9, 0.5],
							"uv": {
								"north": {"uv": [6.75, 1.75], "uv_size": [5.75, 3.5]},
								"east": {"uv": [0, 0], "uv_size": [0.25, 0.25]},
								"south": {"uv": [7.75, 1.75], "uv_size": [5.75, 3.5]},
								"west": {"uv": [0, 0], "uv_size": [0.25, 0.25]},
								"up": {"uv": [0.25, 0.25], "uv_size": [-0.25, -0.25]},
								"down": {"uv": [0.25, 0.25], "uv_size": [-0.25, -0.25]}
							}
						},
						{
							"origin": [-43.2933, 40.51759, -0.25],
							"size": [37.25, 5.75, 0.5],
							"uv": {
								"north": {"uv": [5.25, 14.5], "uv_size": [7.75, 1.5]},
								"east": {"uv": [0, 0], "uv_size": [0.25, 0.25]},
								"south": {"uv": [5.25, 14.5], "uv_size": [7.75, 1.5]},
								"west": {"uv": [0, 0], "uv_size": [0.25, 0.25]},
								"up": {"uv": [0.25, 0.25], "uv_size": [-0.25, -0.25]},
								"down": {"uv": [0.25, 0.25], "uv_size": [-0.25, -0.25]}
							}
						},
						{
							"origin": [-48.7933, 38.76759, -0.25],
							"size": [29.75, 1.75, 0.5],
							"uv": {
								"north": {"uv": [5.75, 12.75], "uv_size": [6, 0.5]},
								"east": {"uv": [0, 0], "uv_size": [0.25, 0.25]},
								"south": {"uv": [3.75, 9.75], "uv_size": [6, 0.5]},
								"west": {"uv": [0, 0], "uv_size": [0.25, 0.25]},
								"up": {"uv": [0.25, 0.25], "uv_size": [-0.25, -0.25]},
								"down": {"uv": [0.25, 0.25], "uv_size": [-0.25, -0.25]}
							}
						},
						{
							"origin": [-46.2933, 40.51759, -0.25],
							"size": [3, 3.25, 0.5],
							"uv": {
								"north": {"uv": [5.5, 12.5], "uv_size": [0.75, 0.75]},
								"east": {"uv": [0, 0], "uv_size": [0.25, 0.25]},
								"south": {"uv": [5.5, 12.5], "uv_size": [0.75, 0.75]},
								"west": {"uv": [0, 0], "uv_size": [0.25, 0.25]},
								"up": {"uv": [0.25, 0.25], "uv_size": [-0.25, -0.25]},
								"down": {"uv": [0.25, 0.25], "uv_size": [-0.25, -0.25]}
							}
						},
						{
							"origin": [-47.2933, 40.51759, -0.25],
							"size": [1, 1.5, 0.5],
							"uv": {
								"north": {"uv": [5.5, 12.5], "uv_size": [0.5, 0.5]},
								"east": {"uv": [0, 0], "uv_size": [0.25, 0.25]},
								"south": {"uv": [5.5, 12.5], "uv_size": [0.5, 0.5]},
								"west": {"uv": [0, 0], "uv_size": [0.25, 0.25]},
								"up": {"uv": [0.25, 0.25], "uv_size": [-0.25, -0.25]},
								"down": {"uv": [0.25, 0.25], "uv_size": [-0.25, -0.25]}
							}
						},
						{
							"origin": [-40.5433, 46.26759, -0.25],
							"size": [1, 1.5, 0.5],
							"uv": {
								"north": {"uv": [5.25, 7.25], "uv_size": [0.5, 0.5]},
								"east": {"uv": [0, 0], "uv_size": [0.25, 0.25]},
								"south": {"uv": [3.75, 7.5], "uv_size": [0.5, 0.5]},
								"west": {"uv": [0, 0], "uv_size": [0.25, 0.25]},
								"up": {"uv": [0.25, 0.25], "uv_size": [-0.25, -0.25]},
								"down": {"uv": [0.25, 0.25], "uv_size": [-0.25, -0.25]}
							}
						},
						{
							"origin": [-34.0433, 37.26759, -0.25],
							"size": [4.25, 1.5, 0.5],
							"uv": {
								"north": {"uv": [10, 12.75], "uv_size": [1, 0.5]},
								"east": {"uv": [0, 0], "uv_size": [0.25, 0.25]},
								"south": {"uv": [10, 12.75], "uv_size": [1, 0.5]},
								"west": {"uv": [0, 0], "uv_size": [0.25, 0.25]},
								"up": {"uv": [0.25, 0.25], "uv_size": [-0.25, -0.25]},
								"down": {"uv": [0.25, 0.25], "uv_size": [-0.25, -0.25]}
							}
						},
						{
							"origin": [-28.7933, 53.26759, -0.25],
							"size": [1.5, 1, 0.5],
							"uv": {
								"north": {"uv": [0, 0], "uv_size": [0.25, 0.25]},
								"east": {"uv": [0, 0], "uv_size": [0.25, 0.25]},
								"south": {"uv": [0, 0], "uv_size": [0.25, 0.25]},
								"west": {"uv": [0, 0], "uv_size": [0.25, 0.25]},
								"up": {"uv": [0.25, 0.25], "uv_size": [-0.25, -0.25]},
								"down": {"uv": [0.25, 0.25], "uv_size": [-0.25, -0.25]}
							}
						},
						{
							"origin": [-22.2933, 55.51759, -0.25],
							"size": [3.25, 1.25, 0.5],
							"uv": {
								"north": {"uv": [0, 0], "uv_size": [0.25, 0.25]},
								"east": {"uv": [0, 0], "uv_size": [0.25, 0.25]},
								"south": {"uv": [0, 0], "uv_size": [0.25, 0.25]},
								"west": {"uv": [0, 0], "uv_size": [0.25, 0.25]},
								"up": {"uv": [0.25, 0.25], "uv_size": [-0.25, -0.25]},
								"down": {"uv": [0.25, 0.25], "uv_size": [-0.25, -0.25]}
							}
						},
						{
							"origin": [-51.5433, 36.01759, -0.25],
							"size": [17.5, 2.75, 0.5],
							"uv": {
								"north": {"uv": [6.75, 12.5], "uv_size": [4.25, 0.75]},
								"east": {"uv": [0, 0], "uv_size": [0.25, 0.25]},
								"south": {"uv": [3, 8.5], "uv_size": [4.25, 0.75]},
								"west": {"uv": [0, 0], "uv_size": [0.25, 0.25]},
								"up": {"uv": [0.25, 0.25], "uv_size": [-0.25, -0.25]},
								"down": {"uv": [0.25, 0.25], "uv_size": [-0.25, -0.25]}
							}
						},
						{
							"origin": [-53.5433, 34.01759, -0.25],
							"size": [13.75, 2, 0.5],
							"uv": {
								"north": {"uv": [7, 12.75], "uv_size": [3.5, 0.5]},
								"east": {"uv": [0, 0], "uv_size": [0.25, 0.25]},
								"south": {"uv": [3.25, 8.75], "uv_size": [3.5, 0.5]},
								"west": {"uv": [0, 0], "uv_size": [0.25, 0.25]},
								"up": {"uv": [0.25, 0.25], "uv_size": [-0.25, -0.25]},
								"down": {"uv": [0.25, 0.25], "uv_size": [-0.25, -0.25]}
							}
						},
						{
							"origin": [-56.0433, 32.01759, -0.25],
							"size": [11.25, 2, 0.5],
							"uv": {
								"north": {"uv": [7.25, 12.75], "uv_size": [3, 0.5]},
								"east": {"uv": [0, 0], "uv_size": [0.25, 0.25]},
								"south": {"uv": [3.25, 9.75], "uv_size": [3, 0.5]},
								"west": {"uv": [0, 0], "uv_size": [0.25, 0.25]},
								"up": {"uv": [0.25, 0.25], "uv_size": [-0.25, -0.25]},
								"down": {"uv": [0.25, 0.25], "uv_size": [-0.25, -0.25]}
							}
						},
						{
							"origin": [-57.7933, 29.76759, -0.25],
							"size": [9.25, 2.25, 0.5],
							"uv": {
								"north": {"uv": [0, 8.5], "uv_size": [2.25, 0.5]},
								"east": {"uv": [0, 0], "uv_size": [0.25, 0.25]},
								"south": {"uv": [0, 8.5], "uv_size": [2.25, 0.5]},
								"west": {"uv": [0, 0], "uv_size": [0.25, 0.25]},
								"up": {"uv": [0.25, 0.25], "uv_size": [-0.25, -0.25]},
								"down": {"uv": [0.25, 0.25], "uv_size": [-0.25, -0.25]}
							}
						},
						{
							"origin": [-59.2933, 27.76759, -0.25],
							"size": [7, 2, 0.5],
							"uv": {
								"north": {"uv": [0, 8], "uv_size": [1.75, 0.5]},
								"east": {"uv": [0, 0], "uv_size": [0.25, 0.25]},
								"south": {"uv": [0, 8], "uv_size": [1.75, 0.5]},
								"west": {"uv": [0, 0], "uv_size": [0.25, 0.25]},
								"up": {"uv": [0.25, 0.25], "uv_size": [-0.25, -0.25]},
								"down": {"uv": [0.25, 0.25], "uv_size": [-0.25, -0.25]}
							}
						},
						{
							"origin": [-61.0433, 25.51759, -0.25],
							"size": [5.5, 2.25, 0.5],
							"uv": {
								"north": {"uv": [0, 8], "uv_size": [1.25, 0.5]},
								"east": {"uv": [0, 0], "uv_size": [0.25, 0.25]},
								"south": {"uv": [0, 8], "uv_size": [1.25, 0.5]},
								"west": {"uv": [0, 0], "uv_size": [0.25, 0.25]},
								"up": {"uv": [0.25, 0.25], "uv_size": [-0.25, -0.25]},
								"down": {"uv": [0.25, 0.25], "uv_size": [-0.25, -0.25]}
							}
						},
						{
							"origin": [-61.5433, 23.26759, -0.25],
							"size": [2.75, 2.25, 0.5],
							"uv": {
								"north": {"uv": [0, 8], "uv_size": [0.5, 0.5]},
								"east": {"uv": [0, 0], "uv_size": [0.25, 0.25]},
								"south": {"uv": [0, 8], "uv_size": [0.5, 0.5]},
								"west": {"uv": [0, 0], "uv_size": [0.25, 0.25]},
								"up": {"uv": [0.25, 0.25], "uv_size": [-0.25, -0.25]},
								"down": {"uv": [0.25, 0.25], "uv_size": [-0.25, -0.25]}
							}
						},
						{
							"origin": [-27.2933, 46.26759, -0.25],
							"size": [8.25, 9.25, 0.5],
							"uv": {
								"north": {"uv": [4.75, 6], "uv_size": [2, 2]},
								"east": {"uv": [0, 0], "uv_size": [0.25, 0.25]},
								"south": {"uv": [5.75, 5.75], "uv_size": [2, 2]},
								"west": {"uv": [0, 0], "uv_size": [0.25, 0.25]},
								"up": {"uv": [0.25, 0.25], "uv_size": [-0.25, -0.25]},
								"down": {"uv": [0.25, 0.25], "uv_size": [-0.25, -0.25]}
							}
						},
						{
							"origin": [-32.0433, 46.26759, -0.25],
							"size": [4.75, 7, 0.5],
							"uv": {
								"north": {"uv": [4.25, 6.25], "uv_size": [1, 1.75]},
								"east": {"uv": [0, 0], "uv_size": [0.25, 0.25]},
								"south": {"uv": [7, 6], "uv_size": [1, 1.75]},
								"west": {"uv": [0, 0], "uv_size": [0.25, 0.25]},
								"up": {"uv": [0.25, 0.25], "uv_size": [-0.25, -0.25]},
								"down": {"uv": [0.25, 0.25], "uv_size": [-0.25, -0.25]}
							}
						},
						{
							"origin": [-36.0433, 46.26759, -0.25],
							"size": [4, 5, 0.5],
							"uv": {
								"north": {"uv": [3.75, 6.5], "uv_size": [0.75, 1.5]},
								"east": {"uv": [0, 0], "uv_size": [0.25, 0.25]},
								"south": {"uv": [8.5, 6.5], "uv_size": [0.75, 1.5]},
								"west": {"uv": [0, 0], "uv_size": [0.25, 0.25]},
								"up": {"uv": [0.25, 0.25], "uv_size": [-0.25, -0.25]},
								"down": {"uv": [0.25, 0.25], "uv_size": [-0.25, -0.25]}
							}
						},
						{
							"origin": [-39.5433, 46.26759, -0.25],
							"size": [3.5, 3, 0.5],
							"uv": {
								"north": {"uv": [6, 6], "uv_size": [0.75, 1.25]},
								"east": {"uv": [0, 0], "uv_size": [0.25, 0.25]},
								"south": {"uv": [7.75, 6.75], "uv_size": [0.75, 0.75]},
								"west": {"uv": [0, 0], "uv_size": [0.25, 0.25]},
								"up": {"uv": [0.25, 0.25], "uv_size": [-0.25, -0.25]},
								"down": {"uv": [0.25, 0.25], "uv_size": [-0.25, -0.25]}
							}
						},
						{
							"origin": [-42.0433, 46.26759, -0.25],
							"size": [2, 0.75, 0.5],
							"uv": {
								"north": {"uv": [0, 0], "uv_size": [0.25, 0.25]},
								"east": {"uv": [0, 0], "uv_size": [0.25, 0.25]},
								"south": {"uv": [0, 0], "uv_size": [0.25, 0.25]},
								"west": {"uv": [0, 0], "uv_size": [0.25, 0.25]},
								"up": {"uv": [0.25, 0.25], "uv_size": [-0.25, -0.25]},
								"down": {"uv": [0.25, 0.25], "uv_size": [-0.25, -0.25]}
							}
						},
						{
							"origin": [-19.0433, 56.51759, -0.25],
							"size": [1, 0.75, 0.5],
							"uv": {
								"north": {"uv": [0, 0], "uv_size": [0.25, 0.25]},
								"east": {"uv": [0, 0], "uv_size": [0.25, 0.25]},
								"south": {"uv": [0, 0], "uv_size": [0.25, 0.25]},
								"west": {"uv": [0, 0], "uv_size": [0.25, 0.25]},
								"up": {"uv": [0.25, 0.25], "uv_size": [-0.25, -0.25]},
								"down": {"uv": [0.25, 0.25], "uv_size": [-0.25, -0.25]}
							}
						}
					]
				},
				{
					"name": "heads",
					"parent": "inner",
					"pivot": [0, -15, 0.75],
					"cubes": [
						{
							"origin": [29.9567, 43.26759, -1.25],
							"size": [6, 6, 3],
							"pivot": [32.9567, 46.26759, 0.25],
							"rotation": [0, 0, -12.5],
							"uv": {
								"north": {"uv": [13.5, 3], "uv_size": [2, 2]},
								"east": {"uv": [13.5, 5], "uv_size": [1, 2]},
								"south": {"uv": [13.5, 3], "uv_size": [2, 2]},
								"west": {"uv": [14.5, 5], "uv_size": [1, 2]},
								"up": {"uv": [15.5, 2.5], "uv_size": [-2, -1]},
								"down": {"uv": [15.5, 2.5], "uv_size": [-2, -1]}
							}
						},
						{
							"origin": [17.59183, 42.59921, -2.25],
							"size": [6, 6, 5],
							"pivot": [20.59183, 46.59921, 0.25],
							"rotation": [0, 0, 37.5],
							"uv": {
								"north": {"uv": [13.5, 3], "uv_size": [2, 2]},
								"east": {"uv": [13.5, 5], "uv_size": [1, 2]},
								"south": {"uv": [13.5, 3], "uv_size": [2, 2]},
								"west": {"uv": [14.5, 5], "uv_size": [1, 2]},
								"up": {"uv": [15.5, 2.5], "uv_size": [-2, -1]},
								"down": {"uv": [15.5, 2.5], "uv_size": [-2, -1]}
							}
						},
						{
							"origin": [21.90619, 42.72881, -2.75],
							"size": [7, 7, 6],
							"pivot": [25.90619, 45.72881, 0.25],
							"rotation": [0, 0, 2.5],
							"uv": {
								"north": {"uv": [13.5, 3], "uv_size": [2, 2]},
								"east": {"uv": [13.5, 5], "uv_size": [1, 2]},
								"south": {"uv": [13.5, 3], "uv_size": [2, 2]},
								"west": {"uv": [14.5, 5], "uv_size": [1, 2]},
								"up": {"uv": [15.5, 2.5], "uv_size": [-2, -1]},
								"down": {"uv": [15.5, 2.5], "uv_size": [-2, -1]}
							}
						},
						{
							"origin": [-0.5262, 55.74197, -2.75],
							"size": [7, 7, 6],
							"pivot": [2.9738, 59.24197, 0.25],
							"rotation": [0, 0, -32.5],
							"uv": {
								"north": {"uv": [13.5, 3], "uv_size": [2, 2]},
								"east": {"uv": [13.5, 5], "uv_size": [1, 2]},
								"south": {"uv": [13.5, 3], "uv_size": [2, 2]},
								"west": {"uv": [14.5, 5], "uv_size": [1, 2]},
								"up": {"uv": [15.5, 2.5], "uv_size": [-2, -1]},
								"down": {"uv": [15.5, 2.5], "uv_size": [-2, -1]}
							}
						},
						{
							"origin": [33.09344, 46.31015, -2.75],
							"size": [6, 6, 6],
							"pivot": [35.59344, 49.81015, 0.25],
							"rotation": [0, 0, 17.5],
							"uv": {
								"north": {"uv": [13.5, 3], "uv_size": [2, 2]},
								"east": {"uv": [13.5, 5], "uv_size": [1, 2]},
								"south": {"uv": [13.5, 3], "uv_size": [2, 2]},
								"west": {"uv": [14.5, 5], "uv_size": [1, 2]},
								"up": {"uv": [15.5, 2.5], "uv_size": [-2, -1]},
								"down": {"uv": [15.5, 2.5], "uv_size": [-2, -1]}
							}
						},
						{
							"origin": [4.25684, 58.36597, -2.25],
							"size": [6, 6, 5],
							"pivot": [7.25684, 61.36597, 0.25],
							"rotation": [0, 0, 10],
							"uv": {
								"north": {"uv": [13.5, 3], "uv_size": [2, 2]},
								"east": {"uv": [13.5, 5], "uv_size": [1, 2]},
								"south": {"uv": [13.5, 3], "uv_size": [2, 2]},
								"west": {"uv": [14.5, 5], "uv_size": [1, 2]},
								"up": {"uv": [15.5, 2.5], "uv_size": [-2, -1]},
								"down": {"uv": [15.5, 2.5], "uv_size": [-2, -1]}
							}
						},
						{
							"origin": [-13.93524, 53.34798, -2.25],
							"size": [6, 6, 5],
							"pivot": [-11.68524, 57.59798, 0.25],
							"rotation": [0, 0, -10],
							"uv": {
								"north": {"uv": [13.5, 3], "uv_size": [2, 2]},
								"east": {"uv": [13.5, 5], "uv_size": [1, 2]},
								"south": {"uv": [13.5, 3], "uv_size": [2, 2]},
								"west": {"uv": [14.5, 5], "uv_size": [1, 2]},
								"up": {"uv": [15.5, 2.5], "uv_size": [-2, -1]},
								"down": {"uv": [15.5, 2.5], "uv_size": [-2, -1]}
							}
						},
						{
							"origin": [-4.31622, 55.81592, -2.25],
							"size": [6, 6, 5],
							"pivot": [-1.31622, 58.81592, 0.25],
							"rotation": [0, 0, -2.5],
							"uv": {
								"north": {"uv": [13.5, 3], "uv_size": [2, 2]},
								"east": {"uv": [13.5, 5], "uv_size": [1, 2]},
								"south": {"uv": [13.5, 3], "uv_size": [2, 2]},
								"west": {"uv": [14.5, 5], "uv_size": [1, 2]},
								"up": {"uv": [15.5, 2.5], "uv_size": [-2, -1]},
								"down": {"uv": [15.5, 2.5], "uv_size": [-2, -1]}
							}
						},
						{
							"origin": [13.9567, 43.26759, -1.45],
							"size": [4, 4, 3.4],
							"pivot": [15.9567, 45.26759, 0.25],
							"rotation": [0, 0, -17.5],
							"uv": {
								"north": {"uv": [13.5, 3], "uv_size": [2, 2]},
								"east": {"uv": [13.5, 5], "uv_size": [1, 2]},
								"south": {"uv": [13.5, 3], "uv_size": [2, 2]},
								"west": {"uv": [14.5, 5], "uv_size": [1, 2]},
								"up": {"uv": [15.5, 2.5], "uv_size": [-2, -1]},
								"down": {"uv": [15.5, 2.5], "uv_size": [-2, -1]}
							}
						},
						{
							"origin": [24.05432, 48.13049, -1.45],
							"size": [4, 4, 3.4],
							"pivot": [28.05432, 50.13049, 0.25],
							"rotation": [0, 0, 15],
							"uv": {
								"north": {"uv": [13.5, 3], "uv_size": [2, 2]},
								"east": {"uv": [13.5, 5], "uv_size": [1, 2]},
								"south": {"uv": [13.5, 3], "uv_size": [2, 2]},
								"west": {"uv": [14.5, 5], "uv_size": [1, 2]},
								"up": {"uv": [15.5, 2.5], "uv_size": [-2, -1]},
								"down": {"uv": [15.5, 2.5], "uv_size": [-2, -1]}
							}
						},
						{
							"origin": [-2.59529, 60.98351, -1.45],
							"size": [4, 4, 3.4],
							"pivot": [-0.59529, 62.98351, 0.25],
							"rotation": [0, 0, -22.5],
							"uv": {
								"north": {"uv": [13.5, 3], "uv_size": [2, 2]},
								"east": {"uv": [13.5, 5], "uv_size": [1, 2]},
								"south": {"uv": [13.5, 3], "uv_size": [2, 2]},
								"west": {"uv": [14.5, 5], "uv_size": [1, 2]},
								"up": {"uv": [15.5, 2.5], "uv_size": [-2, -1]},
								"down": {"uv": [15.5, 2.5], "uv_size": [-2, -1]}
							}
						},
						{
							"origin": [10.22057, 58.58479, -1.55],
							"size": [4, 4, 3.6],
							"pivot": [12.22057, 60.58479, 0.25],
							"rotation": [0, 0, -2.5],
							"uv": {
								"north": {"uv": [13.5, 3], "uv_size": [2, 2]},
								"east": {"uv": [13.5, 5], "uv_size": [1, 2]},
								"south": {"uv": [13.5, 3], "uv_size": [2, 2]},
								"west": {"uv": [14.5, 5], "uv_size": [1, 2]},
								"up": {"uv": [15.5, 2.5], "uv_size": [-2, -1]},
								"down": {"uv": [15.5, 2.5], "uv_size": [-2, -1]}
							}
						},
						{
							"origin": [6.19057, 54.25231, -1.55],
							"size": [4, 4, 3.6],
							"pivot": [10.44057, 55.50231, 0.25],
							"rotation": [0, 0, 22.5],
							"uv": {
								"north": {"uv": [13.5, 3], "uv_size": [2, 2]},
								"east": {"uv": [13.5, 5], "uv_size": [1, 2]},
								"south": {"uv": [13.5, 3], "uv_size": [2, 2]},
								"west": {"uv": [14.5, 5], "uv_size": [1, 2]},
								"up": {"uv": [15.5, 2.5], "uv_size": [-2, -1]},
								"down": {"uv": [15.5, 2.5], "uv_size": [-2, -1]}
							}
						},
						{
							"origin": [1.22057, 61.58479, -1.55],
							"size": [4, 4, 3.6],
							"pivot": [12.22057, 60.58479, 0.25],
							"rotation": [0, 0, -2.5],
							"uv": {
								"north": {"uv": [13.5, 3], "uv_size": [2, 2]},
								"east": {"uv": [13.5, 5], "uv_size": [1, 2]},
								"south": {"uv": [13.5, 3], "uv_size": [2, 2]},
								"west": {"uv": [14.5, 5], "uv_size": [1, 2]},
								"up": {"uv": [15.5, 2.5], "uv_size": [-2, -1]},
								"down": {"uv": [15.5, 2.5], "uv_size": [-2, -1]}
							}
						},
						{
							"origin": [15.01362, 49.89201, -1.45],
							"size": [4, 4, 3.4],
							"pivot": [17.01362, 51.89201, 0.25],
							"rotation": [0, 0, 5],
							"uv": {
								"north": {"uv": [13.5, 3], "uv_size": [2, 2]},
								"east": {"uv": [13.5, 5], "uv_size": [1, 2]},
								"south": {"uv": [13.5, 3], "uv_size": [2, 2]},
								"west": {"uv": [14.5, 5], "uv_size": [1, 2]},
								"up": {"uv": [15.5, 2.5], "uv_size": [-2, -1]},
								"down": {"uv": [15.5, 2.5], "uv_size": [-2, -1]}
							}
						},
						{
							"origin": [4.79021, 47.77499, -1.45],
							"size": [4, 4, 3.4],
							"pivot": [6.79021, 49.77499, 0.25],
							"rotation": [0, 0, -25],
							"uv": {
								"north": {"uv": [13.5, 3], "uv_size": [2, 2]},
								"east": {"uv": [13.5, 5], "uv_size": [1, 2]},
								"south": {"uv": [13.5, 3], "uv_size": [2, 2]},
								"west": {"uv": [14.5, 5], "uv_size": [1, 2]},
								"up": {"uv": [15.5, 2.5], "uv_size": [-2, -1]},
								"down": {"uv": [15.5, 2.5], "uv_size": [-2, -1]}
							}
						},
						{
							"origin": [9.99517, 62.37309, -1.45],
							"size": [4, 4, 3.4],
							"pivot": [11.99517, 63.37309, 0.25],
							"rotation": [0, 0, -32.5],
							"uv": {
								"north": {"uv": [13.5, 3], "uv_size": [2, 2]},
								"east": {"uv": [13.5, 5], "uv_size": [1, 2]},
								"south": {"uv": [13.5, 3], "uv_size": [2, 2]},
								"west": {"uv": [14.5, 5], "uv_size": [1, 2]},
								"up": {"uv": [15.5, 2.5], "uv_size": [-2, -1]},
								"down": {"uv": [15.5, 2.5], "uv_size": [-2, -1]}
							}
						},
						{
							"origin": [11.62667, 45.90897, -1.75],
							"size": [5, 5, 4],
							"pivot": [14.12667, 49.40897, 0.25],
							"rotation": [0, 0, 10],
							"uv": {
								"north": {"uv": [13.5, 3], "uv_size": [2, 2]},
								"east": {"uv": [13.5, 5], "uv_size": [1, 2]},
								"south": {"uv": [13.5, 3], "uv_size": [2, 2]},
								"west": {"uv": [14.5, 5], "uv_size": [1, 2]},
								"up": {"uv": [15.5, 2.5], "uv_size": [-2, -1]},
								"down": {"uv": [15.5, 2.5], "uv_size": [-2, -1]}
							}
						},
						{
							"origin": [-12.93644, 57.33267, -1.75],
							"size": [5, 5, 4],
							"pivot": [-10.43644, 59.83267, 0.25],
							"rotation": [0, 0, -32.5],
							"uv": {
								"north": {"uv": [13.5, 3], "uv_size": [2, 2]},
								"east": {"uv": [13.5, 5], "uv_size": [1, 2]},
								"south": {"uv": [13.5, 3], "uv_size": [2, 2]},
								"west": {"uv": [14.5, 5], "uv_size": [1, 2]},
								"up": {"uv": [15.5, 2.5], "uv_size": [-2, -1]},
								"down": {"uv": [15.5, 2.5], "uv_size": [-2, -1]}
							}
						},
						{
							"origin": [-7.54854, 53.33636, -1.75],
							"size": [5, 5, 4],
							"pivot": [-5.04854, 55.83636, 0.25],
							"rotation": [0, 0, -22.5],
							"uv": {
								"north": {"uv": [13.5, 3], "uv_size": [2, 2]},
								"east": {"uv": [13.5, 5], "uv_size": [1, 2]},
								"south": {"uv": [13.5, 3], "uv_size": [2, 2]},
								"west": {"uv": [14.5, 5], "uv_size": [1, 2]},
								"up": {"uv": [15.5, 2.5], "uv_size": [-2, -1]},
								"down": {"uv": [15.5, 2.5], "uv_size": [-2, -1]}
							}
						},
						{
							"origin": [4.40698, 51.32801, -1.75],
							"size": [5, 5, 4],
							"pivot": [6.40698, 54.57801, 0.25],
							"rotation": [0, 0, -7.5],
							"uv": {
								"north": {"uv": [13.5, 3], "uv_size": [2, 2]},
								"east": {"uv": [13.5, 5], "uv_size": [1, 2]},
								"south": {"uv": [13.5, 3], "uv_size": [2, 2]},
								"west": {"uv": [14.5, 5], "uv_size": [1, 2]},
								"up": {"uv": [15.5, 2.5], "uv_size": [-2, -1]},
								"down": {"uv": [15.5, 2.5], "uv_size": [-2, -1]}
							}
						},
						{
							"origin": [19.39225, 46.22957, -1.75],
							"size": [5, 5, 4],
							"pivot": [17.89225, 47.72957, 0.25],
							"rotation": [0, 0, -22.5],
							"uv": {
								"north": {"uv": [13.5, 3], "uv_size": [2, 2]},
								"east": {"uv": [13.5, 5], "uv_size": [1, 2]},
								"south": {"uv": [13.5, 3], "uv_size": [2, 2]},
								"west": {"uv": [14.5, 5], "uv_size": [1, 2]},
								"up": {"uv": [15.5, 2.5], "uv_size": [-2, -1]},
								"down": {"uv": [15.5, 2.5], "uv_size": [-2, -1]}
							}
						},
						{
							"origin": [24.39225, 35.47957, -2],
							"size": [5, 5, 4],
							"pivot": [17.89225, 47.72957, 0.25],
							"rotation": [0, 0, -22.5],
							"uv": {
								"north": {"uv": [13.5, 3], "uv_size": [2, 2]},
								"east": {"uv": [13.5, 5], "uv_size": [1, 2]},
								"south": {"uv": [13.5, 3], "uv_size": [2, 2]},
								"west": {"uv": [14.5, 5], "uv_size": [1, 2]},
								"up": {"uv": [15.5, 2.5], "uv_size": [-2, -1]},
								"down": {"uv": [15.5, 2.5], "uv_size": [-2, -1]}
							}
						},
						{
							"origin": [37.85519, 45.87488, -2],
							"size": [5, 5, 4],
							"pivot": [40.35519, 48.37488, 0],
							"rotation": [0, 0, -10],
							"uv": {
								"north": {"uv": [13.5, 3], "uv_size": [2, 2]},
								"east": {"uv": [13.5, 5], "uv_size": [1, 2]},
								"south": {"uv": [13.5, 3], "uv_size": [2, 2]},
								"west": {"uv": [14.5, 5], "uv_size": [1, 2]},
								"up": {"uv": [15.5, 2.5], "uv_size": [-2, -1]},
								"down": {"uv": [15.5, 2.5], "uv_size": [-2, -1]}
							}
						},
						{
							"origin": [29.25045, 50.96982, -2],
							"size": [5, 5, 4],
							"pivot": [31.75045, 53.46982, 0],
							"rotation": [0, 0, -2.5],
							"uv": {
								"north": {"uv": [13.5, 3], "uv_size": [2, 2]},
								"east": {"uv": [13.5, 5], "uv_size": [1, 2]},
								"south": {"uv": [13.5, 3], "uv_size": [2, 2]},
								"west": {"uv": [14.5, 5], "uv_size": [1, 2]},
								"up": {"uv": [15.5, 2.5], "uv_size": [-2, -1]},
								"down": {"uv": [15.5, 2.5], "uv_size": [-2, -1]}
							}
						},
						{
							"origin": [9.7772, 41.37478, -1.25],
							"size": [5, 5, 3],
							"pivot": [12.2772, 43.87478, 0.25],
							"rotation": [0, 0, -10],
							"uv": {
								"north": {"uv": [13.5, 3], "uv_size": [2, 2]},
								"east": {"uv": [13.5, 5], "uv_size": [1, 2]},
								"south": {"uv": [13.5, 3], "uv_size": [2, 2]},
								"west": {"uv": [14.5, 5], "uv_size": [1, 2]},
								"up": {"uv": [15.5, 2.5], "uv_size": [-2, -1]},
								"down": {"uv": [15.5, 2.5], "uv_size": [-2, -1]}
							}
						},
						{
							"origin": [23.2743, 39.69297, -1.25],
							"size": [5, 5, 3],
							"pivot": [25.7743, 42.19297, 0.25],
							"rotation": [0, 0, 10],
							"uv": {
								"north": {"uv": [13.5, 3], "uv_size": [2, 2]},
								"east": {"uv": [13.5, 5], "uv_size": [1, 2]},
								"south": {"uv": [13.5, 3], "uv_size": [2, 2]},
								"west": {"uv": [14.5, 5], "uv_size": [1, 2]},
								"up": {"uv": [15.5, 2.5], "uv_size": [-2, -1]},
								"down": {"uv": [15.5, 2.5], "uv_size": [-2, -1]}
							}
						},
						{
							"origin": [41.0243, 47.69297, -1.25],
							"size": [4, 4, 3],
							"pivot": [25.7743, 42.19297, 0.25],
							"rotation": [0, 0, 10],
							"uv": {
								"north": {"uv": [13.5, 3], "uv_size": [2, 2]},
								"east": {"uv": [13.5, 5], "uv_size": [1, 2]},
								"south": {"uv": [13.5, 3], "uv_size": [2, 2]},
								"west": {"uv": [14.5, 5], "uv_size": [1, 2]},
								"up": {"uv": [15.5, 2.5], "uv_size": [-2, -1]},
								"down": {"uv": [15.5, 2.5], "uv_size": [-2, -1]}
							}
						},
						{
							"origin": [11.42582, 50.63561, -1.25],
							"size": [4, 4, 3],
							"pivot": [13.42582, 52.63561, 0.25],
							"rotation": [0, 0, -10],
							"uv": {
								"north": {"uv": [13.5, 3], "uv_size": [2, 2]},
								"east": {"uv": [13.5, 5], "uv_size": [1, 2]},
								"south": {"uv": [13.5, 3], "uv_size": [2, 2]},
								"west": {"uv": [14.5, 5], "uv_size": [1, 2]},
								"up": {"uv": [15.5, 2.5], "uv_size": [-2, -1]},
								"down": {"uv": [15.5, 2.5], "uv_size": [-2, -1]}
							}
						},
						{
							"origin": [-8.30239, 58.28167, -1.25],
							"size": [4, 4, 3],
							"pivot": [-5.05239, 59.53167, 0.25],
							"rotation": [0, 0, 7.5],
							"uv": {
								"north": {"uv": [13.5, 3], "uv_size": [2, 2]},
								"east": {"uv": [13.5, 5], "uv_size": [1, 2]},
								"south": {"uv": [13.5, 3], "uv_size": [2, 2]},
								"west": {"uv": [14.5, 5], "uv_size": [1, 2]},
								"up": {"uv": [15.5, 2.5], "uv_size": [-2, -1]},
								"down": {"uv": [15.5, 2.5], "uv_size": [-2, -1]}
							}
						},
						{
							"origin": [26.42582, 44.63561, -1.5],
							"size": [4, 4, 3.5],
							"pivot": [13.42582, 52.63561, 0.25],
							"rotation": [0, 0, -10],
							"uv": {
								"north": {"uv": [13.5, 3], "uv_size": [2, 2]},
								"east": {"uv": [13.5, 5], "uv_size": [1, 2]},
								"south": {"uv": [13.5, 3], "uv_size": [2, 2]},
								"west": {"uv": [14.5, 5], "uv_size": [1, 2]},
								"up": {"uv": [15.5, 2.5], "uv_size": [-2, -1]},
								"down": {"uv": [15.5, 2.5], "uv_size": [-2, -1]}
							}
						},
						{
							"origin": [8.54775, 49.09947, -1.5],
							"size": [4, 4, 3.5],
							"pivot": [10.29775, 53.09947, 0.25],
							"rotation": [0, 0, 15],
							"uv": {
								"north": {"uv": [13.5, 3], "uv_size": [2, 2]},
								"east": {"uv": [13.5, 5], "uv_size": [1, 2]},
								"south": {"uv": [13.5, 3], "uv_size": [2, 2]},
								"west": {"uv": [14.5, 5], "uv_size": [1, 2]},
								"up": {"uv": [15.5, 2.5], "uv_size": [-2, -1]},
								"down": {"uv": [15.5, 2.5], "uv_size": [-2, -1]}
							}
						},
						{
							"origin": [-2.40948, 52.67437, -1.5],
							"size": [4, 4, 3.5],
							"pivot": [-0.40948, 54.67437, 0.25],
							"rotation": [0, 0, -27.5],
							"uv": {
								"north": {"uv": [13.5, 3], "uv_size": [2, 2]},
								"east": {"uv": [13.5, 5], "uv_size": [1, 2]},
								"south": {"uv": [13.5, 3], "uv_size": [2, 2]},
								"west": {"uv": [14.5, 5], "uv_size": [1, 2]},
								"up": {"uv": [15.5, 2.5], "uv_size": [-2, -1]},
								"down": {"uv": [15.5, 2.5], "uv_size": [-2, -1]}
							}
						},
						{
							"origin": [14.24964, 59.72346, -1.5],
							"size": [4, 4, 3.5],
							"pivot": [16.74964, 61.72346, 0.25],
							"rotation": [0, 0, 15],
							"uv": {
								"north": {"uv": [13.5, 3], "uv_size": [2, 2]},
								"east": {"uv": [13.5, 5], "uv_size": [1, 2]},
								"south": {"uv": [13.5, 3], "uv_size": [2, 2]},
								"west": {"uv": [14.5, 5], "uv_size": [1, 2]},
								"up": {"uv": [15.5, 2.5], "uv_size": [-2, -1]},
								"down": {"uv": [15.5, 2.5], "uv_size": [-2, -1]}
							}
						},
						{
							"origin": [-15.75036, 46.72346, -1.5],
							"size": [4.5, 4.5, 3.5],
							"pivot": [16.74964, 61.72346, 0.25],
							"rotation": [0, 0, 15],
							"uv": {
								"north": {"uv": [13.5, 3], "uv_size": [2, 2]},
								"east": {"uv": [13.5, 5], "uv_size": [1, 2]},
								"south": {"uv": [13.5, 3], "uv_size": [2, 2]},
								"west": {"uv": [14.5, 5], "uv_size": [1, 2]},
								"up": {"uv": [15.5, 2.5], "uv_size": [-2, -1]},
								"down": {"uv": [15.5, 2.5], "uv_size": [-2, -1]}
							}
						},
						{
							"origin": [7.1379, 45.29113, -1.15],
							"size": [3, 3, 2.8],
							"pivot": [8.6379, 49.54113, 0.25],
							"rotation": [0, 0, -17.5],
							"uv": {
								"north": {"uv": [13.5, 3], "uv_size": [2, 2]},
								"east": {"uv": [13.5, 5], "uv_size": [1, 2]},
								"south": {"uv": [13.5, 3], "uv_size": [2, 2]},
								"west": {"uv": [14.5, 5], "uv_size": [1, 2]},
								"up": {"uv": [15.5, 2.5], "uv_size": [-2, -1]},
								"down": {"uv": [15.5, 2.5], "uv_size": [-2, -1]}
							}
						},
						{
							"origin": [2.1379, 52.54113, -1.05],
							"size": [3, 3, 2.6],
							"pivot": [8.6379, 49.54113, 0.25],
							"rotation": [0, 0, -17.5],
							"uv": {
								"north": {"uv": [13.5, 3], "uv_size": [2, 2]},
								"east": {"uv": [13.5, 5], "uv_size": [1, 2]},
								"south": {"uv": [13.5, 3], "uv_size": [2, 2]},
								"west": {"uv": [14.5, 5], "uv_size": [1, 2]},
								"up": {"uv": [15.5, 2.5], "uv_size": [-2, -1]},
								"down": {"uv": [15.5, 2.5], "uv_size": [-2, -1]}
							}
						},
						{
							"origin": [-4.60828, 51.88624, -1.05],
							"size": [3, 3, 2.6],
							"pivot": [-4.10828, 53.38624, 0.25],
							"rotation": [0, 0, 25],
							"uv": {
								"north": {"uv": [13.5, 3], "uv_size": [2, 2]},
								"east": {"uv": [13.5, 5], "uv_size": [1, 2]},
								"south": {"uv": [13.5, 3], "uv_size": [2, 2]},
								"west": {"uv": [14.5, 5], "uv_size": [1, 2]},
								"up": {"uv": [15.5, 2.5], "uv_size": [-2, -1]},
								"down": {"uv": [15.5, 2.5], "uv_size": [-2, -1]}
							}
						},
						{
							"origin": [-9.17244, 51.34148, -1.05],
							"size": [3, 3, 2.6],
							"pivot": [-7.67244, 52.84148, 0.25],
							"rotation": [0, 0, 5],
							"uv": {
								"north": {"uv": [13.5, 3], "uv_size": [2, 2]},
								"east": {"uv": [13.5, 5], "uv_size": [1, 2]},
								"south": {"uv": [13.5, 3], "uv_size": [2, 2]},
								"west": {"uv": [14.5, 5], "uv_size": [1, 2]},
								"up": {"uv": [15.5, 2.5], "uv_size": [-2, -1]},
								"down": {"uv": [15.5, 2.5], "uv_size": [-2, -1]}
							}
						},
						{
							"origin": [-16.25618, 52.71377, -1.05],
							"size": [3, 3, 2.6],
							"pivot": [-14.75618, 54.21377, 0.25],
							"rotation": [0, 0, -12.5],
							"uv": {
								"north": {"uv": [13.5, 3], "uv_size": [2, 2]},
								"east": {"uv": [13.5, 5], "uv_size": [1, 2]},
								"south": {"uv": [13.5, 3], "uv_size": [2, 2]},
								"west": {"uv": [14.5, 5], "uv_size": [1, 2]},
								"up": {"uv": [15.5, 2.5], "uv_size": [-2, -1]},
								"down": {"uv": [15.5, 2.5], "uv_size": [-2, -1]}
							}
						},
						{
							"origin": [-8.76791, 56.91906, -1.15],
							"size": [3, 3, 2.8],
							"pivot": [-7.26791, 58.41906, 0.25],
							"rotation": [0, 0, -2.5],
							"uv": {
								"north": {"uv": [13.5, 3], "uv_size": [2, 2]},
								"east": {"uv": [13.5, 5], "uv_size": [1, 2]},
								"south": {"uv": [13.5, 3], "uv_size": [2, 2]},
								"west": {"uv": [14.5, 5], "uv_size": [1, 2]},
								"up": {"uv": [15.5, 2.5], "uv_size": [-2, -1]},
								"down": {"uv": [15.5, 2.5], "uv_size": [-2, -1]}
							}
						},
						{
							"origin": [21.1379, 56.79113, -1.15],
							"size": [3, 3, 2.8],
							"pivot": [8.6379, 49.54113, 0.25],
							"rotation": [0, 0, -17.5],
							"uv": {
								"north": {"uv": [13.5, 3], "uv_size": [2, 2]},
								"east": {"uv": [13.5, 5], "uv_size": [1, 2]},
								"south": {"uv": [13.5, 3], "uv_size": [2, 2]},
								"west": {"uv": [14.5, 5], "uv_size": [1, 2]},
								"up": {"uv": [15.5, 2.5], "uv_size": [-2, -1]},
								"down": {"uv": [15.5, 2.5], "uv_size": [-2, -1]}
							}
						},
						{
							"origin": [12.29213, 61.7775, -1.15],
							"size": [3, 3, 2.8],
							"pivot": [14.79213, 63.2775, 0.25],
							"rotation": [0, 0, -10],
							"uv": {
								"north": {"uv": [13.5, 3], "uv_size": [2, 2]},
								"east": {"uv": [13.5, 5], "uv_size": [1, 2]},
								"south": {"uv": [13.5, 3], "uv_size": [2, 2]},
								"west": {"uv": [14.5, 5], "uv_size": [1, 2]},
								"up": {"uv": [15.5, 2.5], "uv_size": [-2, -1]},
								"down": {"uv": [15.5, 2.5], "uv_size": [-2, -1]}
							}
						},
						{
							"origin": [9.02176, 52.04283, -1.15],
							"size": [3, 3, 2.8],
							"pivot": [10.52176, 53.54283, 0.25],
							"rotation": [0, 0, 112.5],
							"uv": {
								"north": {"uv": [13.5, 3], "uv_size": [2, 2]},
								"east": {"uv": [13.5, 5], "uv_size": [1, 2]},
								"south": {"uv": [13.5, 3], "uv_size": [2, 2]},
								"west": {"uv": [14.5, 5], "uv_size": [1, 2]},
								"up": {"uv": [15.5, 2.5], "uv_size": [-2, -1]},
								"down": {"uv": [15.5, 2.5], "uv_size": [-2, -1]}
							}
						},
						{
							"origin": [1.78923, 53.12385, -1.15],
							"size": [3, 3, 2.8],
							"pivot": [3.28923, 54.37385, 0.25],
							"rotation": [0, 0, 35],
							"uv": {
								"north": {"uv": [13.5, 3], "uv_size": [2, 2]},
								"east": {"uv": [13.5, 5], "uv_size": [1, 2]},
								"south": {"uv": [13.5, 3], "uv_size": [2, 2]},
								"west": {"uv": [14.5, 5], "uv_size": [1, 2]},
								"up": {"uv": [15.5, 2.5], "uv_size": [-2, -1]},
								"down": {"uv": [15.5, 2.5], "uv_size": [-2, -1]}
							}
						},
						{
							"origin": [15.74493, 47.3472, -1.15],
							"size": [3, 3, 2.8],
							"pivot": [17.24493, 48.8472, 0.25],
							"rotation": [0, 0, 2.5],
							"uv": {
								"north": {"uv": [13.5, 3], "uv_size": [2, 2]},
								"east": {"uv": [13.5, 5], "uv_size": [1, 2]},
								"south": {"uv": [13.5, 3], "uv_size": [2, 2]},
								"west": {"uv": [14.5, 5], "uv_size": [1, 2]},
								"up": {"uv": [15.5, 2.5], "uv_size": [-2, -1]},
								"down": {"uv": [15.5, 2.5], "uv_size": [-2, -1]}
							}
						},
						{
							"origin": [30.74493, 49.3472, -1.15],
							"size": [3, 3, 2.8],
							"pivot": [17.24493, 48.8472, 0.25],
							"rotation": [0, 0, 2.5],
							"uv": {
								"north": {"uv": [13.5, 3], "uv_size": [2, 2]},
								"east": {"uv": [13.5, 5], "uv_size": [1, 2]},
								"south": {"uv": [13.5, 3], "uv_size": [2, 2]},
								"west": {"uv": [14.5, 5], "uv_size": [1, 2]},
								"up": {"uv": [15.5, 2.5], "uv_size": [-2, -1]},
								"down": {"uv": [15.5, 2.5], "uv_size": [-2, -1]}
							}
						},
						{
							"origin": [27.39627, 44.57567, -1.15],
							"size": [3, 3, 2.8],
							"pivot": [29.14627, 46.32567, 0.25],
							"rotation": [0, 0, -52.5],
							"uv": {
								"north": {"uv": [13.5, 3], "uv_size": [2, 2]},
								"east": {"uv": [13.5, 5], "uv_size": [1, 2]},
								"south": {"uv": [13.5, 3], "uv_size": [2, 2]},
								"west": {"uv": [14.5, 5], "uv_size": [1, 2]},
								"up": {"uv": [15.5, 2.5], "uv_size": [-2, -1]},
								"down": {"uv": [15.5, 2.5], "uv_size": [-2, -1]}
							}
						}
					]
				},
				{
					"name": "outer",
					"parent": "main_scythe",
					"pivot": [0, -13, 0],
					"cubes": [
						{
							"origin": [-23.64763, 35.61289, -1],
							"size": [9.5, 2, 2],
							"pivot": [-15.14763, 37.61289, 0],
							"rotation": [0, 0, 20],
							"uv": {
								"north": {"uv": [8.25, 8.5], "uv_size": [2.25, 0.5]},
								"east": {"uv": [8.25, 8], "uv_size": [0.5, 0.5]},
								"south": {"uv": [2.5, 12], "uv_size": [2.25, 0.5]},
								"west": {"uv": [0, 0], "uv_size": [0.5, 0.5]},
								"up": {"uv": [4.75, 12.5], "uv_size": [-2.25, -0.5]},
								"down": {"uv": [4.75, 12.5], "uv_size": [-2.25, -0.5]}
							}
						},
						{
							"origin": [-15.83734, 33.56777, -0.999],
							"size": [5.5, 2, 1.998],
							"pivot": [-13.08734, 34.56777, 0],
							"rotation": [0, 0, 47.5],
							"uv": {
								"north": {"uv": [1.25, 1], "uv_size": [1.25, 0.5]},
								"east": {"uv": [0, 0], "uv_size": [0.5, 0.5]},
								"south": {"uv": [1.25, 1], "uv_size": [1.25, 0.5]},
								"west": {"uv": [0, 0], "uv_size": [0.5, 0.5]},
								"up": {"uv": [2.5, 1.5], "uv_size": [-1.25, -0.5]},
								"down": {"uv": [2.5, 1.5], "uv_size": [-1.25, -0.5]}
							}
						},
						{
							"origin": [-12.60801, 29.35922, -1],
							"size": [5.5, 2, 2],
							"pivot": [-9.85801, 30.35922, 0],
							"rotation": [0, 0, 57.5],
							"uv": {
								"north": {"uv": [1.25, 1], "uv_size": [1.25, 0.5]},
								"east": {"uv": [0, 0], "uv_size": [0.5, 0.5]},
								"south": {"uv": [1.25, 1], "uv_size": [1.25, 0.5]},
								"west": {"uv": [0, 0], "uv_size": [0.5, 0.5]},
								"up": {"uv": [2.5, 1.5], "uv_size": [-1.25, -0.5]},
								"down": {"uv": [2.5, 1.5], "uv_size": [-1.25, -0.5]}
							}
						},
						{
							"origin": [-11.96608, 34.85922, -1],
							"size": [7.5, 2, 2],
							"pivot": [-7.21608, 35.85922, 0],
							"rotation": [0, 0, 122.5],
							"uv": {
								"north": {"uv": [0, 0.5], "uv_size": [1.75, 0.5]},
								"east": {"uv": [0, 0], "uv_size": [0.5, 0.5]},
								"south": {"uv": [0, 0.5], "uv_size": [1.75, 0.5]},
								"west": {"uv": [0, 0], "uv_size": [0.5, 0.5]},
								"up": {"uv": [1.75, 1], "uv_size": [-1.75, -0.5]},
								"down": {"uv": [1.75, 1], "uv_size": [-1.75, -0.5]}
							}
						},
						{
							"origin": [-11.28704, 30.32719, -0.999],
							"size": [5.5, 2, 1.998],
							"pivot": [-8.53704, 31.32719, 0],
							"rotation": [0, 0, 90],
							"uv": {
								"north": {"uv": [0, 1], "uv_size": [1.25, 0.5]},
								"east": {"uv": [0, 0], "uv_size": [0.5, 0.5]},
								"south": {"uv": [0, 1], "uv_size": [1.25, 0.5]},
								"west": {"uv": [0, 0], "uv_size": [0.5, 0.5]},
								"up": {"uv": [1.25, 1.5], "uv_size": [-1.25, -0.5]},
								"down": {"uv": [1.25, 1.5], "uv_size": [-1.25, -0.5]}
							}
						},
						{
							"origin": [-44.48511, 34.48565, -1],
							"size": [10, 2, 2],
							"pivot": [-38.48511, 35.48565, 0],
							"rotation": [0, 0, -20],
							"uv": {
								"north": {"uv": [3.5, 8.5], "uv_size": [2.5, 0.5]},
								"east": {"uv": [0, 0], "uv_size": [0.5, 0.5]},
								"south": {"uv": [7, 12], "uv_size": [2.5, 0.5]},
								"west": {"uv": [0, 0], "uv_size": [0.5, 0.5]},
								"up": {"uv": [9.5, 12.5], "uv_size": [-2.5, -0.5]},
								"down": {"uv": [9.5, 12.5], "uv_size": [-2.5, -0.5]}
							}
						},
						{
							"origin": [-35.35755, 37.83884, -1.001],
							"size": [12.55, 2, 2.002],
							"pivot": [-25.73255, 38.83884, 0],
							"rotation": [0, 0, -12.5],
							"uv": {
								"north": {"uv": [5.25, 8.5], "uv_size": [3, 0.5]},
								"east": {"uv": [0, 0], "uv_size": [0.5, 0.5]},
								"south": {"uv": [4.75, 12], "uv_size": [3, 0.5]},
								"west": {"uv": [0, 0], "uv_size": [0.5, 0.5]},
								"up": {"uv": [7.75, 12.5], "uv_size": [-3, -0.5]},
								"down": {"uv": [7.75, 12.5], "uv_size": [-3, -0.5]}
							}
						},
						{
							"origin": [-55.16144, 29.50719, -0.999],
							"size": [12, 2, 1.998],
							"pivot": [-49.16144, 30.50719, 0],
							"rotation": [0, 0, -30],
							"uv": {
								"north": {"uv": [0.5, 8], "uv_size": [3, 0.5]},
								"east": {"uv": [0, 0], "uv_size": [0.5, 0.5]},
								"south": {"uv": [9.5, 12], "uv_size": [3, 0.5]},
								"west": {"uv": [0, 0], "uv_size": [0.5, 0.5]},
								"up": {"uv": [12.5, 12.5], "uv_size": [-3, -0.5]},
								"down": {"uv": [12.5, 12.5], "uv_size": [-3, -0.5]}
							}
						},
						{
							"origin": [-65.54893, 23.11261, -1],
							"size": [12.35, 2, 2],
							"pivot": [-59.19893, 24.11261, 0],
							"rotation": [0, 0, -35],
							"uv": {
								"north": {"uv": [0, 8], "uv_size": [3, 0.5]},
								"east": {"uv": [0, 8], "uv_size": [0.5, 0.5]},
								"south": {"uv": [10, 12], "uv_size": [3, 0.5]},
								"west": {"uv": [0, 0], "uv_size": [0.5, 0.5]},
								"up": {"uv": [13, 12.5], "uv_size": [-3, -0.5]},
								"down": {"uv": [13, 12.5], "uv_size": [-3, -0.5]}
							}
						},
						{
							"origin": [-67.12592, 25.10461, -1.001],
							"size": [12.25, 2, 2.002],
							"pivot": [-60.87592, 26.10461, 0.002],
							"rotation": [0, 0, -59],
							"uv": {
								"north": {"uv": [4, 8.5], "uv_size": [3, 0.5]},
								"east": {"uv": [0, 0], "uv_size": [0.5, 0.5]},
								"south": {"uv": [6, 12], "uv_size": [3, 0.5]},
								"west": {"uv": [0, 0], "uv_size": [0.5, 0.5]},
								"up": {"uv": [9, 12.5], "uv_size": [-3, -0.5]},
								"down": {"uv": [9, 12.5], "uv_size": [-3, -0.5]}
							}
						},
						{
							"origin": [-56.91062, 27.58067, -1],
							"size": [14.5, 2, 2],
							"pivot": [-60.41062, 28.58067, 0.001],
							"rotation": [0, 0, -45],
							"uv": {
								"north": {"uv": [6.75, 8.5], "uv_size": [3.5, 0.5]},
								"east": {"uv": [0, 0], "uv_size": [0.5, 0.5]},
								"south": {"uv": [2.75, 12], "uv_size": [3.5, 0.5]},
								"west": {"uv": [0, 0], "uv_size": [0.5, 0.5]},
								"up": {"uv": [6.25, 12.5], "uv_size": [-3.5, -0.5]},
								"down": {"uv": [6.25, 12.5], "uv_size": [-3.5, -0.5]}
							}
						},
						{
							"origin": [-32.2266, 35.24235, -1],
							"size": [12, 2, 2],
							"pivot": [-61.2266, 29.24235, 0.003],
							"rotation": [0, 0, -27.5],
							"uv": {
								"north": {"uv": [0, 1], "uv_size": [3, 0.5]},
								"east": {"uv": [0, 0], "uv_size": [0.5, 0.5]},
								"south": {"uv": [0, 1], "uv_size": [3, 0.5]},
								"west": {"uv": [0, 0], "uv_size": [0.5, 0.5]},
								"up": {"uv": [3, 1.5], "uv_size": [-3, -0.5]},
								"down": {"uv": [3, 1.5], "uv_size": [-3, -0.5]}
							}
						},
						{
							"origin": [-39.50422, 31.60274, -1.001],
							"size": [12, 2, 2.002],
							"pivot": [-55.50422, 25.60274, 0.003],
							"rotation": [0, 0, -40],
							"uv": {
								"north": {"uv": [10, 8.5], "uv_size": [3, 0.5]},
								"east": {"uv": [0, 0], "uv_size": [0.5, 0.5]},
								"south": {"uv": [0, 12.5], "uv_size": [3, 0.5]},
								"west": {"uv": [0, 0], "uv_size": [0.5, 0.5]},
								"up": {"uv": [3, 13], "uv_size": [-3, -0.5]},
								"down": {"uv": [3, 13], "uv_size": [-3, -0.5]}
							}
						},
						{
							"origin": [3.5669, 57.13421, -0.999],
							"size": [10.5, 2, 1.998],
							"pivot": [8.5669, 58.13421, 0],
							"rotation": [0, 0, -20],
							"uv": {
								"north": {"uv": [0, 0.75], "uv_size": [2.5, 0.5]},
								"east": {"uv": [0, 0], "uv_size": [0.5, 0.5]},
								"south": {"uv": [0, 0.75], "uv_size": [2.5, 0.5]},
								"west": {"uv": [0, 0], "uv_size": [0.5, 0.5]},
								"up": {"uv": [2.5, 1.25], "uv_size": [-2.5, -0.5]},
								"down": {"uv": [2.5, 1.25], "uv_size": [-2.5, -0.5]}
							}
						},
						{
							"origin": [13.47239, 59.74672, -1],
							"size": [11, 2, 2],
							"pivot": [19.47239, 60.74672, -0.001],
							"rotation": [0, 0, -7.5],
							"uv": {
								"north": {"uv": [0, 0.5], "uv_size": [2.75, 0.5]},
								"east": {"uv": [0, 0], "uv_size": [0.5, 0.5]},
								"south": {"uv": [0, 0.5], "uv_size": [2.75, 0.5]},
								"west": {"uv": [0, 0], "uv_size": [0.5, 0.5]},
								"up": {"uv": [2.75, 1], "uv_size": [-2.75, -0.5]},
								"down": {"uv": [2.75, 1], "uv_size": [-2.75, -0.5]}
							}
						},
						{
							"origin": [22.86562, 51.8878, -1],
							"size": [6, 2, 2],
							"pivot": [29.36562, 52.8878, -0.002],
							"rotation": [0, 0, -15],
							"uv": {
								"north": {"uv": [0, 0.75], "uv_size": [1.5, 0.5]},
								"east": {"uv": [0, 0], "uv_size": [0.5, 0.5]},
								"south": {"uv": [0, 0.75], "uv_size": [1.5, 0.5]},
								"west": {"uv": [0, 0], "uv_size": [0.5, 0.5]},
								"up": {"uv": [1.5, 1.25], "uv_size": [-1.5, -0.5]},
								"down": {"uv": [1.5, 1.25], "uv_size": [-1.5, -0.5]}
							}
						},
						{
							"origin": [27.04305, 53.8235, -1.001],
							"size": [6, 2, 2.002],
							"pivot": [30.04305, 54.8235, 0],
							"rotation": [0, 0, -55],
							"uv": {
								"north": {"uv": [0, 0], "uv_size": [1.5, 0.5]},
								"east": {"uv": [0, 0], "uv_size": [0.5, 0.5]},
								"south": {"uv": [0, 0], "uv_size": [1.5, 0.5]},
								"west": {"uv": [0, 0], "uv_size": [0.5, 0.5]},
								"up": {"uv": [1.5, 0.5], "uv_size": [-1.5, -0.5]},
								"down": {"uv": [1.5, 0.5], "uv_size": [-1.5, -0.5]}
							}
						},
						{
							"origin": [30.71593, 54.2349, -1],
							"size": [6, 2, 2],
							"pivot": [32.71593, 55.2349, 0],
							"rotation": [0, 0, 37.5],
							"uv": {
								"north": {"uv": [0, 0.5], "uv_size": [1.5, 0.5]},
								"east": {"uv": [0, 0], "uv_size": [0.5, 0.5]},
								"south": {"uv": [0, 0.5], "uv_size": [1.5, 0.5]},
								"west": {"uv": [0, 0], "uv_size": [0.5, 0.5]},
								"up": {"uv": [1.5, 1], "uv_size": [-1.5, -0.5]},
								"down": {"uv": [1.5, 1], "uv_size": [-1.5, -0.5]}
							}
						},
						{
							"origin": [35.90527, 54.06515, -1.001],
							"size": [7, 2, 2.002],
							"pivot": [28.90527, 55.06515, 0],
							"rotation": [0, 0, 17.5],
							"uv": {
								"north": {"uv": [0, 0.75], "uv_size": [1.75, 0.5]},
								"east": {"uv": [0, 0], "uv_size": [0.5, 0.5]},
								"south": {"uv": [0, 0.75], "uv_size": [1.75, 0.5]},
								"west": {"uv": [0, 0], "uv_size": [0.5, 0.5]},
								"up": {"uv": [1.75, 1.25], "uv_size": [-1.75, -0.5]},
								"down": {"uv": [1.75, 1.25], "uv_size": [-1.75, -0.5]}
							}
						},
						{
							"origin": [44.0916, 55.29434, -1],
							"size": [11, 2, 2],
							"pivot": [37.0916, 56.29434, -0.001],
							"rotation": [0, 0, 47.5],
							"uv": {
								"north": {"uv": [0, 0.5], "uv_size": [2.75, 0.5]},
								"east": {"uv": [0, 0], "uv_size": [0.5, 0.5]},
								"south": {"uv": [0, 0.5], "uv_size": [2.75, 0.5]},
								"west": {"uv": [0, 0], "uv_size": [0.5, 0.5]},
								"up": {"uv": [2.75, 1], "uv_size": [-2.75, -0.5]},
								"down": {"uv": [2.75, 1], "uv_size": [-2.75, -0.5]}
							}
						},
						{
							"origin": [27.07079, 40.59571, -1],
							"size": [7, 2, 2],
							"pivot": [32.57079, 41.59571, 0.001],
							"rotation": [0, 0, -50],
							"uv": {
								"north": {"uv": [0, 0], "uv_size": [1.75, 0.5]},
								"east": {"uv": [0, 0], "uv_size": [0.5, 0.5]},
								"south": {"uv": [0, 0], "uv_size": [1.75, 0.5]},
								"west": {"uv": [0, 0], "uv_size": [0.5, 0.5]},
								"up": {"uv": [1.75, 0.5], "uv_size": [-1.75, -0.5]},
								"down": {"uv": [1.75, 0.5], "uv_size": [-1.75, -0.5]}
							}
						},
						{
							"origin": [41.71533, 43.1579, -1.001],
							"size": [11, 2, 2.002],
							"pivot": [47.21533, 52.1579, 0],
							"rotation": [0, 0, 20],
							"uv": {
								"north": {"uv": [0, 0.5], "uv_size": [2.75, 0.5]},
								"east": {"uv": [0, 0], "uv_size": [0.5, 0.5]},
								"south": {"uv": [0, 0.5], "uv_size": [2.75, 0.5]},
								"west": {"uv": [0, 0], "uv_size": [0.5, 0.5]},
								"up": {"uv": [2.75, 1], "uv_size": [-2.75, -0.5]},
								"down": {"uv": [2.75, 1], "uv_size": [-2.75, -0.5]}
							}
						},
						{
							"origin": [32.68878, 43.59514, -0.999],
							"size": [8, 2, 1.998],
							"pivot": [36.68878, 44.59514, 0],
							"rotation": [0, 0, -30],
							"uv": {
								"north": {"uv": [0, 0.5], "uv_size": [2, 0.5]},
								"east": {"uv": [0, 0], "uv_size": [0.5, 0.5]},
								"south": {"uv": [0, 0.5], "uv_size": [2, 0.5]},
								"west": {"uv": [0, 0], "uv_size": [0.5, 0.5]},
								"up": {"uv": [2, 1], "uv_size": [-2, -0.5]},
								"down": {"uv": [2, 1], "uv_size": [-2, -0.5]}
							}
						},
						{
							"origin": [16.16098, 41.08486, -1],
							"size": [10, 2, 2],
							"pivot": [21.16098, 42.08486, 0.001],
							"rotation": [0, 0, 12.5],
							"uv": {
								"north": {"uv": [0, 0.5], "uv_size": [2.5, 0.5]},
								"east": {"uv": [0, 0], "uv_size": [0.5, 0.5]},
								"south": {"uv": [0, 0.5], "uv_size": [2.5, 0.5]},
								"west": {"uv": [0, 0], "uv_size": [0.5, 0.5]},
								"up": {"uv": [2.5, 1], "uv_size": [-2.5, -0.5]},
								"down": {"uv": [2.5, 1], "uv_size": [-2.5, -0.5]}
							}
						},
						{
							"origin": [25.0302, 38.35932, -0.999],
							"size": [6, 2, 1.998],
							"pivot": [28.0302, 39.35932, 0],
							"rotation": [0, 0, 37.5],
							"uv": {
								"north": {"uv": [0, 0.5], "uv_size": [1.25, 0.5]},
								"east": {"uv": [0, 0], "uv_size": [0.5, 0.5]},
								"south": {"uv": [0, 0.5], "uv_size": [1.25, 0.5]},
								"west": {"uv": [0, 0], "uv_size": [0.5, 0.5]},
								"up": {"uv": [1.25, 1], "uv_size": [-1.25, -0.5]},
								"down": {"uv": [1.25, 1], "uv_size": [-1.25, -0.5]}
							}
						},
						{
							"origin": [-19.77849, 57.4909, -1],
							"size": [11.25, 2, 2],
							"pivot": [-13.77849, 58.4909, 0],
							"rotation": [0, 0, -10],
							"uv": {
								"north": {"uv": [0, 0.75], "uv_size": [3, 0.5]},
								"east": {"uv": [0, 0], "uv_size": [0.5, 0.5]},
								"south": {"uv": [0, 0.75], "uv_size": [3, 0.5]},
								"west": {"uv": [0, 0], "uv_size": [0.5, 0.5]},
								"up": {"uv": [3, 1.25], "uv_size": [-3, -0.5]},
								"down": {"uv": [3, 1.25], "uv_size": [-3, -0.5]}
							}
						},
						{
							"origin": [-28.40712, 54.442, -0.999],
							"size": [9.25, 2, 1.998],
							"pivot": [-25.15712, 55.442, 0],
							"rotation": [0, 0, -20],
							"uv": {
								"north": {"uv": [0, 0.5], "uv_size": [2.25, 0.5]},
								"east": {"uv": [0, 0], "uv_size": [0.5, 0.5]},
								"south": {"uv": [0, 0.5], "uv_size": [2.25, 0.5]},
								"west": {"uv": [0, 0], "uv_size": [0.5, 0.5]},
								"up": {"uv": [2.25, 1], "uv_size": [-2.25, -0.5]},
								"down": {"uv": [2.25, 1], "uv_size": [-2.25, -0.5]}
							}
						},
						{
							"origin": [-19.40712, 54.942, -1.001],
							"size": [25.5, 2, 2.002],
							"pivot": [-25.15712, 55.442, 0],
							"rotation": [0, 0, -15],
							"uv": {
								"north": {"uv": [0, 4.5], "uv_size": [6.25, 0.5]},
								"east": {"uv": [0, 0], "uv_size": [0.5, 0.5]},
								"south": {"uv": [0, 4.5], "uv_size": [6.25, 0.5]},
								"west": {"uv": [0, 0], "uv_size": [0.5, 0.5]},
								"up": {"uv": [6.25, 5], "uv_size": [-6.25, -0.5]},
								"down": {"uv": [6.25, 5], "uv_size": [-6.25, -0.5]}
							}
						},
						{
							"origin": [4.63983, 62.97899, -1],
							"size": [10, 2, 2],
							"uv": {
								"north": {"uv": [0, 0.75], "uv_size": [2.5, 0.5]},
								"east": {"uv": [0, 0], "uv_size": [0.5, 0.5]},
								"south": {"uv": [0, 0.75], "uv_size": [2.5, 0.5]},
								"west": {"uv": [0, 0], "uv_size": [0.5, 0.5]},
								"up": {"uv": [2.5, 1.25], "uv_size": [-2.5, -0.5]},
								"down": {"uv": [2.5, 1.25], "uv_size": [-2.5, -0.5]}
							}
						},
						{
							"origin": [14.21064, 61.71897, -0.999],
							"size": [10, 2, 1.998],
							"pivot": [19.21064, 62.71897, 0],
							"rotation": [0, 0, 15],
							"uv": {
								"north": {"uv": [0, 1.25], "uv_size": [2.5, 0.5]},
								"east": {"uv": [0, 0], "uv_size": [0.5, 0.5]},
								"south": {"uv": [0, 1.25], "uv_size": [2.5, 0.5]},
								"west": {"uv": [0, 0], "uv_size": [0.5, 0.5]},
								"up": {"uv": [2.5, 1.75], "uv_size": [-2.5, -0.5]},
								"down": {"uv": [2.5, 1.75], "uv_size": [-2.5, -0.5]}
							}
						},
						{
							"origin": [3.77526, 39.25889, -1],
							"size": [8, 2, 2],
							"pivot": [8.77526, 40.25889, 0],
							"rotation": [0, 0, -10],
							"uv": {
								"north": {"uv": [0, 1], "uv_size": [1.75, 0.5]},
								"east": {"uv": [0, 0], "uv_size": [0.5, 0.5]},
								"south": {"uv": [0, 1], "uv_size": [1.75, 0.5]},
								"west": {"uv": [0, 0], "uv_size": [0.5, 0.5]},
								"up": {"uv": [1.75, 1.5], "uv_size": [-1.75, -0.5]},
								"down": {"uv": [1.75, 1.5], "uv_size": [-1.75, -0.5]}
							}
						},
						{
							"origin": [11.19964, 40.96919, -0.999],
							"size": [6, 2, 1.998],
							"pivot": [14.19964, 41.96919, -0.001],
							"rotation": [0, 0, -25],
							"uv": {
								"north": {"uv": [0, 0], "uv_size": [1.25, 0.5]},
								"east": {"uv": [0, 0], "uv_size": [0.5, 0.5]},
								"south": {"uv": [0, 0], "uv_size": [1.25, 0.5]},
								"west": {"uv": [0, 0], "uv_size": [0.5, 0.5]},
								"up": {"uv": [1.25, 0.5], "uv_size": [-1.25, -0.5]},
								"down": {"uv": [1.25, 0.5], "uv_size": [-1.25, -0.5]}
							}
						},
						{
							"origin": [3.29864, 54.57452, -1],
							"size": [11.25, 2, 2],
							"pivot": [8.67364, 55.57452, 0.001],
							"rotation": [0, 0, 10],
							"uv": {
								"north": {"uv": [0, 0], "uv_size": [2.75, 0.5]},
								"east": {"uv": [0, 0], "uv_size": [0.5, 0.5]},
								"south": {"uv": [0, 0], "uv_size": [2.75, 0.5]},
								"west": {"uv": [0, 0], "uv_size": [0.5, 0.5]},
								"up": {"uv": [2.75, 0.5], "uv_size": [-2.75, -0.5]},
								"down": {"uv": [2.75, 0.5], "uv_size": [-2.75, -0.5]}
							}
						},
						{
							"origin": [14.65286, 55.65157, -1.001],
							"size": [10, 2, 2.002],
							"pivot": [8.65286, 56.65157, 0],
							"rotation": [0, 0, 20],
							"uv": {
								"north": {"uv": [0, 1.25], "uv_size": [2.5, 0.5]},
								"east": {"uv": [0, 0], "uv_size": [0.5, 0.5]},
								"south": {"uv": [0, 1.25], "uv_size": [2.5, 0.5]},
								"west": {"uv": [0, 0], "uv_size": [0.5, 0.5]},
								"up": {"uv": [2.5, 1.75], "uv_size": [-2.5, -0.5]},
								"down": {"uv": [2.5, 1.75], "uv_size": [-2.5, -0.5]}
							}
						}
					]
				}
			]
		}
	]
}